MANIFEST.in
README.txt
setup.py
WebHooksDemo.egg-info/PKG-INFO
WebHooksDemo.egg-info/SOURCES.txt
WebHooksDemo.egg-info/dependency_links.txt
WebHooksDemo.egg-info/top_level.txt
web_hooks/__init__.py
web_hooks/web_hooks.py