Metadata-Version: 1.0
Name: WebHooksDemo
Version: 0.1
Summary: Example package - testing webhooks on github and python build process
Home-page: UNKNOWN
Author: Nathan Leiby
Author-email: nathanleiby@gmail.com
License: MIT
Platform: UNKNOWN
